profile_me/__init__.py
profile_me-0.1.0.dist-info/METADATA
profile_me-0.1.0.dist-info/WHEEL
profile_me-0.1.0.dist-info/licenses/LICENSE
profile_me-0.1.0.dist-info/RECORD
