Metadata-Version: 2.4
Name: profile-me
Version: 0.1.0
Summary: Enable external profiler attachment for Python processes
Project-URL: Homepage, https://github.com/deepankarsharma/profile-me
Project-URL: Documentation, https://github.com/deepankarsharma/profile-me
Project-URL: Repository, https://github.com/deepankarsharma/profile-me
Author: Deepankar Sharma
License-Expression: MIT
License-File: LICENSE
Keywords: debugging,performance,profiling,ptrace,py-spy,yantra
Classifier: Development Status :: 4 - Beta
Classifier: Environment :: Console
Classifier: Intended Audience :: Developers
Classifier: License :: OSI Approved :: MIT License
Classifier: Operating System :: POSIX :: Linux
Classifier: Programming Language :: Python :: 3
Classifier: Programming Language :: Python :: 3.8
Classifier: Programming Language :: Python :: 3.9
Classifier: Programming Language :: Python :: 3.10
Classifier: Programming Language :: Python :: 3.11
Classifier: Programming Language :: Python :: 3.12
Classifier: Programming Language :: Python :: 3.13
Classifier: Programming Language :: Python :: 3.14
Classifier: Topic :: Software Development :: Debuggers
Classifier: Topic :: System :: Monitoring
Requires-Python: >=3.8
